{"stats":{"minecraft:killed":{"minecraft:skeleton":1,"minecraft:trader_llama":4,"minecraft:chicken":1},"minecraft:mined":{"minecraft:farmland":2,"minecraft:torch":1,"minecraft:dark_oak_fence":3,"minecraft:grass_block":14,"minecraft:chest":1,"minecraft:orange_shulker_box":1,"minecraft:blue_bed":1,"minecraft:smooth_stone":6,"minecraft:light_weighted_pressure_plate":1,"minecraft:purple_bed":1,"minecraft:glowstone":7,"minecraft:wheat":3,"minecraft:light_gray_shulker_box":1,"minecraft:grass":1,"minecraft:dirt":4,"minecraft:purple_shulker_box":1,"minecraft:white_shulker_box":1,"minecraft:blue_shulker_box":1,"minecraft:ender_chest":1},"minecraft:picked_up":{"minecraft:wheat":32,"minecraft:nether_wart":29,"minecraft:light_gray_shulker_box":1,"minecraft:leather":2,"minecraft:lead":3,"minecraft:purple_shulker_box":1,"minecraft:music_disc_cat":2,"minecraft:dirt":36,"minecraft:item_frame":9,"minecraft:wheat_seeds":272,"minecraft:smooth_stone":6,"minecraft:heart_of_the_sea":3,"minecraft:light_weighted_pressure_plate":1,"minecraft:stone_pickaxe":1,"minecraft:bamboo":148,"minecraft:glowstone_dust":12,"minecraft:blue_shulker_box":1,"minecraft:chest":1,"minecraft:egg":64,"minecraft:orange_shulker_box":1,"minecraft:music_disc_13":1,"minecraft:torch":4,"minecraft:redstone":64,"minecraft:dragon_egg":1,"minecraft:leather_helmet":1,"minecraft:arrow":1,"minecraft:gold_ingot":12,"minecraft:glistering_melon_slice":1,"minecraft:white_shulker_box":1,"minecraft:melon_seeds":1,"minecraft:dark_oak_fence":3,"minecraft:obsidian":8},"minecraft:dropped":{"minecraft:obsidian":8,"minecraft:light_weighted_pressure_plate":1,"minecraft:dirt":2,"minecraft:torch":2,"minecraft:glistering_melon_slice":1},"minecraft:killed_by":{"minecraft:player":2,"minecraft:skeleton":1},"minecraft:custom":{"minecraft:interact_with_smithing_table":11,"minecraft:mob_kills":7,"minecraft:interact_with_anvil":1,"minecraft:play_record":1,"minecraft:interact_with_cartography_table":1,"minecraft:interact_with_crafting_table":5,"minecraft:open_shulker_box":5,"minecraft:leave_game":2,"minecraft:time_since_death":630,"minecraft:time_since_rest":650,"minecraft:sprint_one_cm":16891,"minecraft:open_enderchest":1,"minecraft:damage_taken":2709,"minecraft:walk_one_cm":84380,"minecraft:drop":14,"minecraft:damage_dealt":1925,"minecraft:swim_one_cm":36,"minecraft:fly_one_cm":56603,"minecraft:player_kills":2,"minecraft:open_chest":50,"minecraft:crouch_one_cm":3499,"minecraft:play_time":38998,"minecraft:deaths":9,"minecraft:sneak_time":2191,"minecraft:walk_under_water_one_cm":74808,"minecraft:jump":327,"minecraft:walk_on_water_one_cm":10082,"minecraft:total_world_time":38998,"minecraft:fall_one_cm":9333},"minecraft:broken":{"minecraft:golden_sword":1},"minecraft:crafted":{"minecraft:diamond_sword":1,"minecraft:diamond_axe":1,"minecraft:air":0,"minecraft:stick":16,"minecraft:dark_oak_planks":8},"minecraft:used":{"minecraft:netherite_chestplate":1,"minecraft:ender_pearl":1,"minecraft:cooked_chicken":3,"minecraft:dragon_egg":1,"minecraft:dirt":1,"minecraft:music_disc_cat":1,"minecraft:netherite_leggings":1,"minecraft:iron_pickaxe":13,"minecraft:netherite_axe":27,"minecraft:stone_axe":7,"minecraft:golden_sword":33,"minecraft:beef":3,"minecraft:dark_oak_fence":3,"minecraft:egg":186,"minecraft:smooth_stone":6}},"DataVersion":2730}